{"species":"Ipomoea pes-caprae","nodes":[{"l":"IpASR","t":"g","p":1,"x":166.7,"y":1600.0},{"l":"IpNAC10","t":"g","p":1,"x":730.1,"y":483.8},{"l":"IpNAC12","t":"g","p":1,"x":1057.9,"y":0.0},{"l":"IpNAC5","t":"g","p":1,"x":1392.3,"y":76.2},{"l":"IpNAC8","t":"g","p":1,"x":1600.0,"y":604.5},{"l":"IpWRKY16","t":"g","p":1,"x":1526.1,"y":1254.0},{"l":"IpcHKT1;1","t":"g","p":1,"x":1144.9,"y":1513.8},{"l":"IpcHKT1;2","t":"g","p":1,"x":893.9,"y":1484.7},{"l":"Ion homeostasis","t":"p","p":1131,"x":1168.6,"y":774.2},{"l":"Reactive oxygen species (ROS) signalling","t":"p","p":1509,"x":0.0,"y":1169.7}],"edges":[{"s":3,"t":8,"r":"activates_pathway","c":"medium","n":1},{"s":4,"t":8,"r":"activates_pathway","c":"medium","n":1},{"s":1,"t":8,"r":"activates_pathway","c":"medium","n":1},{"s":2,"t":8,"r":"activates_pathway","c":"medium","n":1},{"s":5,"t":8,"r":"activates_pathway","c":"medium","n":1},{"s":6,"t":8,"r":"member_of","c":"high","n":1},{"s":7,"t":8,"r":"member_of","c":"high","n":1},{"s":0,"t":9,"r":"inhibits_pathway","c":"medium","n":1,"e":1},{"s":6,"t":7,"r":"is_paralog_of","c":"high","n":1,"e":1}]}