{"species":"Populus simonii × Populus nigra","nodes":[{"l":"ERF76","t":"g","p":1,"x":1389.2,"y":1384.5},{"l":"HP1","t":"g","p":1,"x":44.9,"y":400.6},{"l":"PsnGT1","t":"g","p":1,"x":322.3,"y":0.0},{"l":"PsnMYB","t":"g","p":1,"x":485.2,"y":85.9},{"l":"PsnMYB30","t":"g","p":1,"x":807.9,"y":1401.0},{"l":"PsnNAC090","t":"g","p":1,"x":406.3,"y":1590.6},{"l":"PsnNAM","t":"g","p":1,"x":360.9,"y":638.7},{"l":"PsnWRKY70","t":"g","p":2,"x":268.1,"y":268.8},{"l":"RRM","t":"g","p":1,"x":499.6,"y":315.8},{"l":"Ulp1","t":"g","p":1,"x":0.0,"y":195.7},{"l":"ABA biosynthesis","t":"p","p":123,"x":1393.6,"y":1600.0},{"l":"ABA signalling","t":"p","p":1566,"x":201.8,"y":1592.9},{"l":"Gibberellin biosynthesis","t":"p","p":30,"x":1600.0,"y":1320.6},{"l":"Photosynthesis","t":"p","p":274,"x":113.2,"y":14.8},{"l":"Reactive oxygen species (ROS) signalling","t":"p","p":1509,"x":614.3,"y":1460.6}],"edges":[{"s":5,"t":14,"r":"activates_pathway","c":"medium","n":1,"e":1},{"s":4,"t":14,"r":"activates_pathway","c":"medium","n":1,"e":1},{"s":7,"t":13,"r":"inhibits_pathway","c":"medium","n":1,"e":1},{"s":1,"t":7,"r":"interacts_with","c":"medium","n":1,"e":1},{"s":5,"t":11,"r":"member_of","c":"medium","n":1},{"s":6,"t":7,"r":"transcribes_target","c":"medium","n":1,"e":1},{"s":3,"t":7,"r":"transcribes_target","c":"medium","n":1,"e":1},{"s":2,"t":7,"r":"transcribes_target","c":"medium","n":1,"e":1},{"s":0,"t":10,"r":"activates_pathway","c":"medium","n":1,"e":1},{"s":0,"t":12,"r":"activates_pathway","c":"medium","n":1,"e":1},{"s":8,"t":7,"r":"interacts_with","c":"medium","n":1,"e":1},{"s":9,"t":7,"r":"interacts_with","c":"medium","n":1,"e":1},{"s":7,"t":8,"r":"interacts_with","c":"medium","n":1,"e":1},{"s":7,"t":9,"r":"interacts_with","c":"medium","n":1,"e":1},{"s":7,"t":7,"r":"transcribes_target","c":"medium","n":1,"e":1}]}