{"species":"Syntrichia caninervis","nodes":[{"l":"ScALDH21","t":"g","p":1,"x":1110.3,"y":460.7},{"l":"ScDREB10","t":"g","p":2,"x":444.4,"y":1129.5},{"l":"ScDREB5","t":"g","p":1,"x":284.7,"y":101.5},{"l":"Auxin signalling","t":"p","p":218,"x":1330.8,"y":0.0},{"l":"Calcium signalling","t":"p","p":232,"x":1600.0,"y":426.9},{"l":"Phenylpropanoid biosynthesis","t":"p","p":28,"x":540.0,"y":1600.0},{"l":"Photosynthesis","t":"p","p":274,"x":849.3,"y":968.4},{"l":"Reactive oxygen species (ROS) signalling","t":"p","p":1509,"x":571.4,"y":523.0},{"l":"Starch and sucrose metabolism","t":"p","p":3,"x":885.2,"y":1394.5},{"l":"Trehalose biosynthesis","t":"p","p":69,"x":0.0,"y":967.4}],"edges":[{"s":2,"t":7,"r":"activates_pathway","c":"medium","n":1,"e":1},{"s":1,"t":5,"r":"activates_pathway","c":"high","n":1},{"s":1,"t":8,"r":"activates_pathway","c":"high","n":1,"e":1},{"s":1,"t":7,"r":"activates_pathway","c":"medium","n":1,"e":1},{"s":0,"t":3,"r":"activates_pathway","c":"medium","n":1,"e":1},{"s":0,"t":4,"r":"activates_pathway","c":"medium","n":1},{"s":0,"t":7,"r":"activates_pathway","c":"medium","n":1,"e":1},{"s":0,"t":6,"r":"activates_pathway","c":"medium","n":1,"e":1},{"s":1,"t":9,"r":"activates_pathway","c":"medium","n":1,"e":1}]}