{"species":"Trichosanthes kirilowii","nodes":[{"l":"TkBBX17","t":"g","p":1,"x":1103.0,"y":1571.9},{"l":"TkBBX2","t":"g","p":1,"x":0.0,"y":621.4},{"l":"TkBBX25","t":"g","p":1,"x":1345.4,"y":0.0},{"l":"TkBBX3","t":"g","p":1,"x":923.6,"y":13.3},{"l":"TkBBX4","t":"g","p":1,"x":418.4,"y":628.1},{"l":"TkBBX5","t":"g","p":1,"x":1600.0,"y":259.7},{"l":"TkBBX7","t":"g","p":1,"x":768.2,"y":1600.0}],"edges":[{"s":6,"t":0,"r":"is_paralog_of","c":"medium","n":1,"e":1},{"s":1,"t":4,"r":"is_paralog_of","c":"medium","n":1,"e":1},{"s":2,"t":3,"r":"is_paralog_of","c":"medium","n":1,"e":1},{"s":2,"t":5,"r":"is_paralog_of","c":"medium","n":1,"e":1},{"s":0,"t":6,"r":"is_paralog_of","c":"medium","n":1,"e":1}]}